secure/__init__.py
secure/py.typed
secure/secure.py
secure/headers/__init__.py
secure/headers/_validation.py
secure/headers/base_header.py
secure/headers/cache_control.py
secure/headers/content_security_policy.py
secure/headers/cross_origin_embedder_policy.py
secure/headers/cross_origin_opener_policy.py
secure/headers/cross_origin_resource_policy.py
secure/headers/custom_header.py
secure/headers/permissions_policy.py
secure/headers/referrer_policy.py
secure/headers/server.py
secure/headers/strict_transport_security.py
secure/headers/x_content_type_options.py
secure/headers/x_dns_prefetch_control.py
secure/headers/x_frame_options.py
secure/headers/x_permitted_cross_domain_policies.py
secure/middleware/__init__.py
secure/middleware/asgi.py
secure/middleware/wsgi.py
secure-2.0.0.dist-info/licenses/LICENSE
secure-2.0.0.dist-info/METADATA
secure-2.0.0.dist-info/WHEEL
secure-2.0.0.dist-info/top_level.txt
secure-2.0.0.dist-info/RECORD
