Metadata-Version: 2.4
Name: secure
Version: 2.0.0
Summary: A lightweight package that adds security headers for Python web frameworks.
Author-email: Caleb Kinney <caleb@typeerror.com>
License-Expression: MIT
Project-URL: Homepage, https://github.com/TypeError/secure
Project-URL: Documentation, https://github.com/TypeError/secure/tree/main/docs
Project-URL: Repository, https://github.com/TypeError/secure
Project-URL: Issue Tracker, https://github.com/TypeError/secure/issues
Keywords: security,headers,web,framework,HTTP
Classifier: Development Status :: 5 - Production/Stable
Classifier: Intended Audience :: Developers
Classifier: Operating System :: OS Independent
Classifier: Programming Language :: Python :: 3
Classifier: Programming Language :: Python :: 3 :: Only
Classifier: Programming Language :: Python :: 3.10
Classifier: Programming Language :: Python :: 3.11
Classifier: Programming Language :: Python :: 3.12
Classifier: Programming Language :: Python :: 3.13
Classifier: Typing :: Typed
Classifier: Topic :: Software Development :: Libraries
Requires-Python: >=3.10
License-File: LICENSE
Dynamic: license-file
